mostx/__init__.py
mostx/langs/__init__.py
mostx/langs/chinese.py
mostx/langs/english.py
mostx/langs/japanese.py
mostx/langs/korean.py
mostx-0.1.1.dev0.dist-info/LICENSE
mostx-0.1.1.dev0.dist-info/WHEEL
mostx-0.1.1.dev0.dist-info/METADATA
mostx-0.1.1.dev0.dist-info/RECORD
