Metadata-Version: 2.1
Name: mostx
Version: 0.1.1.dev0
Summary: Quiz Generator
Home-page: https://github.com/gottadiveintopython/mostx
License: MIT
Keywords: Quiz,Game
Author: Nattōsai Mitō
Author-email: flow4re2c@gmail.com
Requires-Python: >=3.7,<4.0
Classifier: Development Status :: 3 - Alpha
Classifier: Intended Audience :: Education
Classifier: License :: OSI Approved :: MIT License
Classifier: Operating System :: OS Independent
Classifier: Programming Language :: Python
Classifier: Programming Language :: Python :: 3
Classifier: Programming Language :: Python :: 3.7
Classifier: Programming Language :: Python :: 3.8
Classifier: Topic :: Education
Classifier: Topic :: Software Development :: Libraries :: Python Modules
Project-URL: Repository, https://github.com/gottadiveintopython/mostx
